api/__init__.py
api/__main__.py
pixai_api/__init__.py
pixai_openapi/__init__.py
pixai_openapi-0.0.2.dist-info/LICENSE
pixai_openapi-0.0.2.dist-info/METADATA
pixai_openapi-0.0.2.dist-info/WHEEL
pixai_openapi-0.0.2.dist-info/top_level.txt
pixai_openapi-0.0.2.dist-info/RECORD
