Metadata-Version: 2.1
Name: pixai-openapi
Version: 0.0.2
Author: HTony03
Author-email: HTony03 <HTony03@foxmail.com>
Project-URL: Homepage, https://github.com/HTony03/pixai-api-linker
Project-URL: Issues, https://github.com/HTony03/pixai-api-linker/issues
Keywords: python
Classifier: Programming Language :: Python :: 3
Classifier: License :: OSI Approved :: MIT License
Classifier: Operating System :: OS Independent
Requires-Python: >=3.8
License-File: LICENSE
Requires-Dist: requests >=2.32.3
Requires-Dist: pillow >=10.3.0
